{"variants": {"normal": {"model": "mkultra:steampoweredorbblock"}, "poweredstate=6": {"model": "mkultra:steampoweredorb6"}, "poweredstate=7": {"model": "mkultra:steampoweredorb7"}, "poweredstate=4": {"model": "mkultra:steampoweredorb4"}, "poweredstate=5": {"model": "mkultra:steampoweredorb5"}, "poweredstate=2": {"model": "mkultra:steampoweredorb2"}, "poweredstate=3": {"model": "mkultra:steampoweredorb3"}, "poweredstate=0": {"model": "mkultra:steampoweredorbpowereddown"}, "poweredstate=1": {"model": "mkultra:steampoweredorb1"}}}