{
  "slotItems": {
    "mkweapons:main_hand": [
      {
        "itemStack": "{id: \"mkweapons:katana_iron\", Count: 1b, tag: {Damage: 0}}",
        "weight": 1.0
      }
    ],
    "mkweapons:earrings": [
      {
        "itemStack": "{id: \"mkweapons:gold_earring\", Count: 1b}",
        "weight": 1.0
      }
    ]
  },
  "options": [
    {
      "randomizationType": "mkweapons:melee_effect",
      "slotName": "mkweapons:randomization.effect",
      "slots": [
        "mkweapons:main_hand"
      ],
      "weight": 1.0,
      "effects": [
        {
          "itemEffectType": "mkweapons:weapon_effect.undead_damage",
          "multiplier": 1.25
        }
      ]
    },
    {
      "randomizationType": "mkweapons:name",
      "slotName": "mkweapons:randomization.name",
      "slots": [
        "mkweapons:main_hand"
      ],
      "weight": 1.0,
      "name": "{\"text\":\"Stinging Blade\"}"
    },
    {
      "randomizationType": "mkweapons:attributes",
      "slotName": "mkweapons:randomization.attributes",
      "slots": [
        "mkweapons:main_hand"
      ],
      "weight": 1.0,
      "modifiers": [
        {
          "Name": "mkultra:trooper_captain",
          "Amount": 2.0,
          "Operation": 0,
          "UUID": "fc632dd9-9a95-46fb-a1e0-338f8143a6fa",
          "AttributeName": "minecraft:generic.max_health"
        }
      ],
      "unique": true
    },
    {
      "randomizationType": "mkweapons:attributes",
      "slotName": "mkweapons:randomization.attributes",
      "slots": [
        "mkweapons:main_hand"
      ],
      "weight": 1.0,
      "modifiers": [
        {
          "Name": "mkultra:trooper_captain",
          "Amount": 2.0,
          "Operation": 0,
          "UUID": "b5c648e4-c2ac-4713-bf1a-71d5bd4b446a",
          "AttributeName": "mkcore:max_mana"
        }
      ],
      "unique": true
    },
    {
      "randomizationType": "mkweapons:attributes",
      "slotName": "mkweapons:randomization.attributes",
      "slots": [
        "mkweapons:main_hand"
      ],
      "weight": 1.0,
      "modifiers": [
        {
          "Name": "mkultra:trooper_captain",
          "Amount": 0.25,
          "Operation": 0,
          "UUID": "0d1bd89b-1bfb-4a7c-8ec9-29a1fa91b234",
          "AttributeName": "mkcore:mana_regen"
        }
      ],
      "unique": true
    },
    {
      "randomizationType": "mkweapons:attributes",
      "slotName": "mkweapons:randomization.attributes",
      "slots": [
        "mkweapons:main_hand"
      ],
      "weight": 1.0,
      "modifiers": [
        {
          "Name": "mkultra:trooper_captain",
          "Amount": 0.05,
          "Operation": 2,
          "UUID": "3337273a-9d0f-43ae-98c3-d535f71da94e",
          "AttributeName": "minecraft:generic.movement_speed"
        }
      ],
      "unique": true
    },
    {
      "randomizationType": "mkweapons:attributes",
      "slotName": "mkweapons:randomization.attributes",
      "slots": [
        "mkweapons:main_hand"
      ],
      "weight": 1.0,
      "modifiers": [
        {
          "Name": "mkultra:trooper_captain",
          "Amount": 1.0,
          "Operation": 0,
          "UUID": "729389fc-2a71-470b-8834-01efbafde71a",
          "AttributeName": "minecraft:generic.attack_damage"
        }
      ],
      "unique": true
    },
    {
      "randomizationType": "mkweapons:attributes",
      "slotName": "mkweapons:randomization.attributes",
      "slots": [
        "mkweapons:main_hand"
      ],
      "weight": 1.0,
      "modifiers": [
        {
          "Name": "mkultra:trooper_captain",
          "Amount": 1.0,
          "Operation": 0,
          "UUID": "c8cd131c-e179-4567-ac8b-22773bbe657e",
          "AttributeName": "minecraft:generic.armor"
        }
      ],
      "unique": true
    },
    {
      "randomizationType": "mkweapons:attributes",
      "slotName": "mkweapons:randomization.attributes",
      "slots": [
        "mkweapons:main_hand"
      ],
      "weight": 1.0,
      "modifiers": [
        {
          "Name": "mkultra:trooper_captain",
          "Amount": 1.0,
          "Operation": 0,
          "UUID": "c929d13b-150f-4aca-8fc6-d03119367154",
          "AttributeName": "mkcore:nature_damage"
        }
      ],
      "unique": true
    },
    {
      "randomizationType": "mkweapons:attributes",
      "slotName": "mkweapons:randomization.attributes",
      "slots": [
        "mkweapons:earrings"
      ],
      "weight": 1.0,
      "modifiers": [
        {
          "Name": "mkultra:trooper_captain",
          "Amount": 4.0,
          "Operation": 0,
          "UUID": "84a72fe1-809a-4574-b133-2ff7f6b74305",
          "AttributeName": "minecraft:generic.max_health"
        }
      ],
      "unique": true
    },
    {
      "randomizationType": "mkweapons:name",
      "slotName": "mkweapons:randomization.name",
      "slots": [
        "mkweapons:earrings"
      ],
      "weight": 1.0,
      "name": "{\"text\":\"Earring of Minor Health\"}"
    }
  ],
  "templates": [
    {
      "template": {
        "templateType": "mkultra:blade_crit",
        "lootSlot": "mkweapons:main_hand",
        "slots": [
          "mkweapons:randomization.effect",
          "mkweapons:randomization.name",
          "mkweapons:randomization.attributes"
        ]
      },
      "weight": 1.0
    },
    {
      "template": {
        "templateType": "mkultra:earring",
        "lootSlot": "mkweapons:earrings",
        "slots": [
          "mkweapons:randomization.attributes",
          "mkweapons:randomization.name"
        ]
      },
      "weight": 15.0
    },
    {
      "template": {
        "templateType": "mkultra:blade",
        "lootSlot": "mkweapons:main_hand",
        "slots": [
          "mkweapons:randomization.effect",
          "mkweapons:randomization.name"
        ]
      },
      "weight": 10.0
    }
  ]
}